adenosine/__init__.py
adenosine-0.0.0.dist-info/LICENSE
adenosine-0.0.0.dist-info/METADATA
adenosine-0.0.0.dist-info/WHEEL
adenosine-0.0.0.dist-info/top_level.txt
adenosine-0.0.0.dist-info/RECORD
