Metadata-Version: 2.1
Name: adenosine
Version: 0.0.0
Summary: Basic, enthusiast-grade python client for atproto.com and bsky.app
Author-email: bryan newbold <bnewbold@robocracy.org>
Project-URL: Homepage, https://gitlab.com/bnewbold/adenosine
Project-URL: Bug Tracker, https://gitlab.com/bnewbold/adenosine/-/issues
Classifier: Programming Language :: Python :: 3
Classifier: License :: OSI Approved :: MIT License
Classifier: Operating System :: OS Independent
Requires-Python: >=3.8
License-File: LICENSE
